array_as_vcf/__init__.py
array_as_vcf/cli.py
array_as_vcf/lookup.py
array_as_vcf/readers.py
array_as_vcf/utils.py
array_as_vcf/variation.py
array_as_vcf-1.1.0.dist-info/LICENSE
array_as_vcf-1.1.0.dist-info/METADATA
array_as_vcf-1.1.0.dist-info/WHEEL
array_as_vcf-1.1.0.dist-info/entry_points.txt
array_as_vcf-1.1.0.dist-info/top_level.txt
array_as_vcf-1.1.0.dist-info/RECORD
