Metadata-Version: 2.1
Name: array-as-vcf
Version: 1.1.0
Summary: Convert SNP array to VCF
Author: Leiden University Medical Center
Author-email: KG_bioinf@lumc.nl
License: MIT
Keywords: array,vcf,SNP,convert,OpenArray,Cytoscan,lumi370k,lumi317k,Affymetrix
Classifier: Topic :: Scientific/Engineering :: Bio-Informatics
Requires-Python: >=3.6
License-File: LICENSE
